uni_model/__init__.py
uni_model/version.py
uni_model/auto_generated/DataFormat.py
uni_model/auto_generated/EmptyShape.py
uni_model/auto_generated/Layout.py
uni_model/auto_generated/PlaceholderDtype.py
uni_model/auto_generated/ResizeMethod.py
uni_model/auto_generated/Semantic.py
uni_model/auto_generated/SerializationInfo.py
uni_model/auto_generated/Shape.py
uni_model/auto_generated/ShapeImpl.py
uni_model/auto_generated/TensorDesc.py
uni_model/auto_generated/UniLayerAbs.py
uni_model/auto_generated/UniLayerAdd.py
uni_model/auto_generated/UniLayerArgMax.py
uni_model/auto_generated/UniLayerAvgPool.py
uni_model/auto_generated/UniLayerBatchNorm.py
uni_model/auto_generated/UniLayerBiasAdd.py
uni_model/auto_generated/UniLayerBinary.py
uni_model/auto_generated/UniLayerBroadcast.py
uni_model/auto_generated/UniLayerCast.py
uni_model/auto_generated/UniLayerClip.py
uni_model/auto_generated/UniLayerConcat.py
uni_model/auto_generated/UniLayerConstStructure.py
uni_model/auto_generated/UniLayerConv2D.py
uni_model/auto_generated/UniLayerConv2DTranspose.py
uni_model/auto_generated/UniLayerCos.py
uni_model/auto_generated/UniLayerDecode.py
uni_model/auto_generated/UniLayerDiv.py
uni_model/auto_generated/UniLayerEqual.py
uni_model/auto_generated/UniLayerExp.py
uni_model/auto_generated/UniLayerExpandDims.py
uni_model/auto_generated/UniLayerFasterRCNNBoxDecode.py
uni_model/auto_generated/UniLayerFullyConnected.py
uni_model/auto_generated/UniLayerFusedBatchNorm.py
uni_model/auto_generated/UniLayerGelu.py
uni_model/auto_generated/UniLayerGroupNorm.py
uni_model/auto_generated/UniLayerHardSigmoid.py
uni_model/auto_generated/UniLayerHardSwish.py
uni_model/auto_generated/UniLayerIdentity.py
uni_model/auto_generated/UniLayerLayerNorm.py
uni_model/auto_generated/UniLayerMatMulBias.py
uni_model/auto_generated/UniLayerMatmul.py
uni_model/auto_generated/UniLayerMax.py
uni_model/auto_generated/UniLayerMaxPool.py
uni_model/auto_generated/UniLayerMin.py
uni_model/auto_generated/UniLayerMul.py
uni_model-10.0.23.dist-info/LICENSE.txt
uni_model-10.0.23.dist-info/METADATA
uni_model-10.0.23.dist-info/NOTICE.txt
uni_model-10.0.23.dist-info/WHEEL
uni_model-10.0.23.dist-info/top_level.txt
uni_model-10.0.23.dist-info/RECORD
