Metadata-Version: 2.1
Name: uni-model
Version: 10.0.23
Summary: Sony Semiconductor Israel, Uni Model
Home-page: UNKNOWN
Author: ssi-dnn-dev
Author-email: ssi-dnn-dev@sony.com
Maintainer: ssi-dnn-dev
Maintainer-email: ssi-dnn-dev@sony.com
License: UNKNOWN
Platform: UNKNOWN
Requires-Dist: protobuf==4.25.5
Requires-Dist: stringcase
Requires-Dist: numpy
Requires-Dist: networkx
